tinuisheet/__init__.py
tinuisheet-0.2.0.dist-info/licenses/LICENSE
tinuisheet-0.2.0.dist-info/METADATA
tinuisheet-0.2.0.dist-info/WHEEL
tinuisheet-0.2.0.dist-info/top_level.txt
tinuisheet-0.2.0.dist-info/RECORD
