Metadata-Version: 2.4
Name: tinuisheet
Version: 0.2.0
Summary: tinui高级表格
Author-email: Smart-Space <smart-space@qq.com>
License-Expression: Apache-2.0
Project-URL: Repository, https://github.com/Smart-Space/TinUISheet
Classifier: Programming Language :: Python :: 3
Classifier: Operating System :: OS Independent
Requires-Python: >=3.8
License-File: LICENSE
Requires-Dist: tinui
Dynamic: license-file
